otf2ttf/__init__.py
otf2ttf/cli.py
otf2ttf-0.2.dist-info/LICENSE.txt
otf2ttf-0.2.dist-info/METADATA
otf2ttf-0.2.dist-info/WHEEL
otf2ttf-0.2.dist-info/entry_points.txt
otf2ttf-0.2.dist-info/top_level.txt
otf2ttf-0.2.dist-info/RECORD
