Metadata-Version: 2.1
Name: otf2ttf
Version: 0.2
Summary: command-line tool for converting OTF to TTF
Home-page: https://github.com/awesometoolbox/otf2ttf
Author: Awesome Toolbox
Author-email: info@awesometoolbox.com
License: MIT
Keywords: font convert otf ttf
Platform: UNKNOWN
Classifier: Development Status :: 5 - Production/Stable
Classifier: Environment :: Console
Classifier: Environment :: Other Environment
Classifier: Intended Audience :: Developers
Classifier: Intended Audience :: End Users/Desktop
Classifier: License :: OSI Approved :: MIT License
Classifier: Natural Language :: English
Classifier: Operating System :: OS Independent
Classifier: Programming Language :: Python
Classifier: Programming Language :: Python :: 2
Classifier: Programming Language :: Python :: 3
Classifier: Topic :: Text Processing :: Fonts
Classifier: Topic :: Multimedia :: Graphics
Classifier: Topic :: Multimedia :: Graphics :: Graphics Conversion
Requires-Dist: fonttools
Requires-Dist: cu2qu
